[   {"id": 1, "nombre": "Curry-9-Taking-Cookies","precio":159,"jugador":"Curry","cantidad":1, "imagen":"https://basketworld.com/19415-home_default/curry-9-taking-cookies.jpg"},
    {"id": 2, "nombre": "Curry-9-Talking-Trash","precio": 159,"jugador":"Curry","cantidad":1, "imagen": "https://basketworld.com/19411-home_default/curry-9-talking-trash.jpg"},
    {"id": 3,"nombre":  "Curry-9-Close-It-out","precio": 159,"jugador":"Curry", "cantidad":1, "imagen": "https://basketworld.com/19315-home_default/curry-9-close-it-out.jpg"},
    {"id": 4, "nombre": "Curry-9-Elmo","precio": 159,"jugador":"Curry","cantidad":1, "imagen": "https://basketworld.com/18989-home_default/curry-9-elmo.jpg"},
    {"id": 5, "nombre": "SC-3zero-5-White","precio": 89.90,"jugador":"Curry","cantidad":1, "imagen": "https://basketworld.com/18906-home_default/sc-3zero-5-white.jpg"},
    {"id": 6, "nombre": "Curry-9-Count-It","precio": 159,"jugador":"Curry","cantidad":1, "imagen": "https://basketworld.com/18619-home_default/curry-9-count-it.jpg"},
    {"id": 7, "nombre": "Curry-9-Elmo-Junior","precio": 129,"jugador":"Curry","cantidad":1, "imagen": "https://basketworld.com/19310-home_default/curry-9-elmo-junior.jpg"},
    {"id": 8, "nombre": "Curry-9-Play-Big-Junior","precio": 129,"jugador":"Curry","cantidad":1, "imagen": "https://basketworld.com/18956-home_default/curry-9-play-big-junior.jpg"},
    {"id": 9, "nombre": "Kyrie-Flytrap-V-Triple-Black","precio": 89,"jugador":"Irving","cantidad":1, "imagen": "https://basketworld.com/19814-home_default/kyrie-flytrap-v-triple-black.jpg"},
    {"id": 10, "nombre": "Kyrie-Flytrap-v-White-Volt","precio": 89,"jugador":"Irving","cantidad":1, "imagen": "https://basketworld.com/19655-home_default/kyrie-flytrap-v-white-volt.jpg"},
    {"id": 11, "nombre": "Kyrie-Infinity-Keep-Sue-Fresh","precio": 129,"jugador":"Irving", "imagen": "https://basketworld.com/19444-home_default/kyrie-infinity-keep-sue-fresh.jpg"},
    {"id": 12, "nombre": "Kyrie-Infinity-Purple","precio": 129,"jugador":"Irving","cantidad":1, "imagen": "https://basketworld.com/19428-home_default/kyrie-infinity-purple.jpg"},
    {"id": 13, "nombre": "Kyrie-Infinity-Fire-And-Ice","precio": 129,"jugador":"Irving","cantidad":1,"imagen": "https://basketworld.com/19333-home_default/kyrie-infinity-001.jpg"},
    {"id": 14, "nombre": "Harden-6-Black-And-White","precio": 149,"jugador":"Harden","cantidad":1, "imagen": "https://basketworld.com/19762-home_default/harden-6-black-and-white.jpg"},
    {"id": 15, "nombre": "Harden-Stepback-3-Magic-Lilac","precio": 89.90,"jugador":"Harden","cantidad":1, "imagen": "https://basketworld.com/19993-home_default/harden-stepback-3-magic-lilac.jpg"},
    {"id": 16, "nombre": "Harden-Stepback-2-Future","precio": 89,"jugador":"Harden","cantidad":1, "imagen": "https://basketworld.com/16909-home_default/harden-stepback-2-future.jpg"},
    {"id": 17, "nombre": "Giannis-Immortality-Artic-Orange","precio": 79.90,"jugador":"Giannis","cantidad":1, "imagen": "https://basketworld.com/19957-home_default/giannis-immortality-artic-orange.jpg"},
    {"id": 18, "nombre": "giannis-Immortality-Rose","precio": 79.90,"jugador":"Giannis","cantidad":1, "imagen": "https://basketworld.com/19434-home_default/giannis-immortality-rose.jpg"},
    {"id": 19, "nombre": "zoom-Freak-3-Valentine-S-Day","precio": 124.90,"jugador":"Giannis","cantidad":1, "imagen": "https://basketworld.com/19907-home_default/zoom-freak-3-valentine-s-day.jpg"},
    {"id": 20, "nombre": "Zoom-Freak-3-Black","precio": 124.90,"jugador":"Giannis","cantidad":1, "imagen": "https://basketworld.com/19153-home_default/zoom-freak-3-black.jpg"},
    {"id": 21, "nombre": "Zoom-Freak-3-Bred","precio": 124.90,"jugador":"Giannis","cantidad":1, "imagen": "https://basketworld.com/19225-home_default/zoom-freak-3-bred.jpg"},
    {"id": 22, "nombre": "Lebron-xix-Low-Blac","precio": 159.90,"jugador":"James","cantidad":1, "imagen": "https://basketworld.com/20075-home_default/lebron-xix-low-black.jpg"},
    {"id": 23, "nombre": "Lebron-xix-Hard-Hat","precio": 189,"jugador":"James","cantidad":1, "imagen": "https://basketworld.com/20071-home_default/lebron-xix-hard-hat.jpg"},
    {"id": 24, "nombre": "Lebron-Witness-vi-easter","precio": 109,"jugador":"James","cantidad":1, "imagen": "https://basketworld.com/19925-home_default/lebron-witness-vi-easter.jpg"},
    {"id": 25, "nombre": "Lebron-xix-Bred","precio": 189,"jugador":"James","cantidad":1, "imagen": "https://basketworld.com/19231-home_default/lebron-xix-bred.jpg"},
    {"id": 26, "nombre": "Lebron-Witness-vi-Black","precio": 109,"jugador":"James","cantidad":1, "imagen": "https://basketworld.com/18601-home_default/lebron-witness-vi-black.jpg"},
    {"id": 27, "nombre": "Lebron-xix-Hardwood-Classic","precio": 189,"jugador":"James","cantidad":1, "imagen": "https://basketworld.com/19398-home_default/lebron-xix-hardwood-classic.jpg"},
    {"id": 28, "nombre": "PG-6-White","precio": 119,"jugador":"George","cantidad":1, "imagen": "https://basketworld.com/19615-home_default/pg-6-white.jpg"},
    {"id": 29, "nombre": "PG-6-Black-Mint","precio": 119,"jugador":"George","cantidad":1, "imagen": "https://basketworld.com/19524-home_default/pg-6-black-mint.jpg"},
    {"id": 30, "nombre": "PG-5-Silver","precio": 95.20,"jugador":"George","cantidad":1, "imagen": "https://basketworld.com/19032-home_default/pg-5-silver.jpg"},
    {"id": 31, "nombre": "KD-Trey-5-x-Wolf-Grey","precio": 99.90,"jugador":"Durant","cantidad":1, "imagen": "https://basketworld.com/20081-home_default/kd-trey-5-x-wolf-grey.jpg"},
    {"id": 32, "nombre": "KD15-White","precio": 149,"jugador":"Durant","cantidad":1, "imagen": "https://basketworld.com/20024-home_default/kd15-white.jpg"},
    {"id": 33, "nombre": "kd14-nrg-ky-d","precio": 149,"jugador":"Durant","cantidad":1, "imagen": "https://basketworld.com/18917-home_default/kd14-nrg-ky-d.jpg"},
    {"id": 34, "nombre": "KD-Trey-5-ix-Pure-Platinum","precio": 99,"jugador":"Durant","cantidad":1, "imagen": "https://basketworld.com/18812-home_default/kd-trey-5-ix-pure-platinum.jpg"},
    {"id": 35, "nombre": "KD14-Seasonal-Black-Laser","precio": 149,"jugador":"Durant","cantidad":1, "imagen": "https://basketworld.com/18807-home_default/kd14-seasonal-black-laser.jpg"},
    {"id": 36, "nombre": "KD14-Home","precio": 149,"jugador":"Durant","cantidad":1, "imagen": "https://basketworld.com/17212-home_default/kd14-home.jpg"},
    {"id": 37, "nombre": "KD14-Floral","precio": 149,"jugador":"Durant","cantidad":1, "imagen": "https://basketworld.com/16849-home_default/kd14-floral.jpg"},
    {"id": 38, "nombre": "KD14-Multicolor", "precio": 149,"jugador":"Durant","cantidad":1, "imagen":" https://basketworld.com/18020-home_default/kd14-multicolor.jpg" }]